synctera_client_v1/__init__.py
synctera_client_v1/api/__init__.py
synctera_client_v1/api/applications_beta_api.py
synctera_client_v1/api/card_transaction_simulations_beta_api.py
synctera_client_v1/api/card_webhook_simulations_beta_api.py
synctera_client_v1/api/cards_beta_api.py
synctera_client_v1/api/digital_wallet_tokens_beta_api.py
synctera_client_v1/api/external_cards_beta_api.py
synctera_client_v1/api/spend_controls_beta_api.py
synctera_client_v1/api/statements_api.py
synctera_client_v1/api/transactions_beta_api.py
synctera_client_v1/api/webhooks_api.py
synctera_client_v1/api_client.py
synctera_client_v1/api_response.py
synctera_client_v1/configuration.py
synctera_client_v1/exceptions.py
synctera_client_v1/models/__init__.py
synctera_client_v1/models/account_summary.py
synctera_client_v1/models/account_summary_balance_ceiling.py
synctera_client_v1/models/account_summary_balance_floor.py
synctera_client_v1/models/ach_transaction.py
synctera_client_v1/models/ach_transaction_all_of.py
synctera_client_v1/models/ach_transaction_data.py
synctera_client_v1/models/ach_transaction_subtypes.py
synctera_client_v1/models/address.py
synctera_client_v1/models/address1.py
synctera_client_v1/models/adverse_action_reason_code.py
synctera_client_v1/models/all_application_status.py
synctera_client_v1/models/all_transaction_subtypes.py
synctera_client_v1/models/apple_digital_wallet_provision_request.py
synctera_client_v1/models/apple_digital_wallet_provision_response.py
synctera_client_v1/models/applicant.py
synctera_client_v1/models/application.py
synctera_client_v1/models/application_list.py
synctera_client_v1/models/application_list_all_of.py
synctera_client_v1/models/application_patch.py
synctera_client_v1/models/application_response.py
synctera_client_v1/models/application_type.py
synctera_client_v1/models/auth_request_model.py
synctera_client_v1/models/authorization_advice_model.py
synctera_client_v1/models/balance_inquiry_request_model.py
synctera_client_v1-1.41.5.dist-info/METADATA
synctera_client_v1-1.41.5.dist-info/WHEEL
synctera_client_v1-1.41.5.dist-info/RECORD
