Metadata-Version: 2.1
Name: synctera_client_v1
Version: 1.41.5
Summary: Synctera API Client generated by openapi-generator
Home-page: https://github.com/SwadeshInc/synctera-client
Author: Swadesh
Author-email: dev@swadesh.co
Maintainer: D. Kasi Pavan Kumar
Maintainer-email: kasi@swadesh.co
Requires-Python: >=3.9,<4.0
Classifier: Programming Language :: Python :: 3
Classifier: Programming Language :: Python :: 3.9
Classifier: Programming Language :: Python :: 3.10
Classifier: Programming Language :: Python :: 3.11
Requires-Dist: aenum (>=3.1.11)
Requires-Dist: pydantic (>=1.10.5)
Requires-Dist: python-dateutil (>=2.8.2)
Requires-Dist: urllib3 (>=1.25.3)
Project-URL: Repository, https://github.com/SwadeshInc/synctera-client
